penta/__init__.py
penta/conf.py
penta/constants.py
penta/context.py
penta/decorators.py
penta/errors.py
penta/files.py
penta/filter_schema.py
penta/main.py
penta/operation.py
penta/pagination.py
penta/parser.py
penta/patch_dict.py
penta/py.typed
penta/renderers.py
penta/request.py
penta/responses.py
penta/router.py
penta/schema.py
penta/throttling.py
penta/types.py
penta/utils.py
penta/compatibility/__init__.py
penta/compatibility/files.py
penta/compatibility/util.py
penta/crud/__init__.py
penta/crud/decorators.py
penta/crud/exceptions.py
penta/crud/py.typed
penta/crud/routers.py
penta/crud/types.py
penta/crud/viewsets/__init__.py
penta/crud/viewsets/asynchrone.py
penta/crud/viewsets/base.py
penta/crud/viewsets/synchrone.py
penta/dependencies/__init__.py
penta/dependencies/custom.py
penta/dependencies/depends.py
penta/dependencies/header.py
penta/dependencies/query_params.py
penta/dependencies/request.py
penta/management/__init__.py
penta/management/utils.py
penta/management/commands/__init__.py
penta/management/commands/export_openapi_schema.py
penta/openapi/__init__.py
penta/openapi/docs.py
penta/openapi/schema.py
penta/openapi/urls.py
penta/openapi/views.py
penta/orm/__init__.py
penta/orm/factory.py
penta/orm/fields.py
penta/orm/metaclass.py
penta/orm/shortcuts.py
penta/params/__init__.py
penta/params/functions.py
penta/params/models.py
penta/security/__init__.py
penta/security/apikey.py
penta/security/base.py
penta/security/http.py
penta/security/session.py
penta/signature/__init__.py
penta/signature/details.py
penta/signature/parser.py
penta/signature/transformers.py
penta/signature/utils.py
penta/static/ninja/favicon.png
penta/static/ninja/redoc.standalone.js
penta/static/ninja/redoc.standalone.js.map
penta/static/ninja/swagger-ui-bundle.js
penta/static/ninja/swagger-ui-bundle.js.map
penta/static/ninja/swagger-ui-init.js
penta/static/ninja/swagger-ui.css
penta/static/ninja/swagger-ui.css.map
penta/templates/ninja/redoc.html
penta-0.3.2.dist-info/licenses/LICENSE
penta-0.3.2.dist-info/METADATA
penta-0.3.2.dist-info/WHEEL
penta-0.3.2.dist-info/top_level.txt
penta-0.3.2.dist-info/RECORD
