Metadata-Version: 2.4
Name: penta
Version: 0.3.2
Summary: Penta - A web framework for building APIs with Django and Python type hints.
Author-email: Vitaliy Kucheryaviy <ppr.vitaly@gmail.com>
Project-URL: Documentation, https://django-ninja.dev
Project-URL: Repository, https://github.com/vitalik/django-ninja
Classifier: Intended Audience :: Information Technology
Classifier: Intended Audience :: System Administrators
Classifier: Operating System :: OS Independent
Classifier: Development Status :: 5 - Production/Stable
Classifier: Topic :: Internet
Classifier: Topic :: Software Development :: Libraries :: Application Frameworks
Classifier: Topic :: Software Development :: Libraries :: Python Modules
Classifier: Topic :: Software Development :: Libraries
Classifier: Topic :: Software Development
Classifier: Typing :: Typed
Classifier: Environment :: Web Environment
Classifier: Intended Audience :: Developers
Classifier: License :: OSI Approved :: MIT License
Classifier: Programming Language :: Python :: 3
Classifier: Programming Language :: Python :: 3.7
Classifier: Programming Language :: Python :: 3.8
Classifier: Programming Language :: Python :: 3.9
Classifier: Programming Language :: Python :: 3.10
Classifier: Programming Language :: Python :: 3.11
Classifier: Programming Language :: Python :: 3.12
Classifier: Programming Language :: Python :: 3.13
Classifier: Programming Language :: Python :: 3 :: Only
Classifier: Framework :: Django
Classifier: Framework :: Django :: 3.1
Classifier: Framework :: Django :: 3.2
Classifier: Framework :: Django :: 4.1
Classifier: Framework :: Django :: 4.2
Classifier: Framework :: Django :: 5.0
Classifier: Framework :: Django :: 5.1
Classifier: Framework :: Django :: 5.2
Classifier: Framework :: AsyncIO
Classifier: Topic :: Internet :: WWW/HTTP :: HTTP Servers
Classifier: Topic :: Internet :: WWW/HTTP
Requires-Python: >=3.10
License-File: LICENSE
Requires-Dist: Django<6.0,>=3.1
Requires-Dist: fast-depends>=2.4.12
Requires-Dist: pydantic<3.0.0,>=2.0
Requires-Dist: ruff>=0.5.7
Provides-Extra: test
Requires-Dist: pytest; extra == "test"
Requires-Dist: pytest-cov; extra == "test"
Requires-Dist: pytest-django; extra == "test"
Requires-Dist: pytest-asyncio; extra == "test"
Requires-Dist: psycopg2-binary; extra == "test"
Requires-Dist: mypy==1.7.1; extra == "test"
Requires-Dist: ruff==0.5.7; extra == "test"
Requires-Dist: django-stubs; extra == "test"
Provides-Extra: doc
Requires-Dist: mkdocs; extra == "doc"
Requires-Dist: mkdocs-material; extra == "doc"
Requires-Dist: markdown-include; extra == "doc"
Requires-Dist: mkdocstrings; extra == "doc"
Provides-Extra: dev
Requires-Dist: pre-commit; extra == "dev"
Dynamic: license-file
